{
  "name": "plotql",
  "rules": {
    "query": {
      "type": "SEQ",
      "members": [
        {
          "type": "SYMBOL",
          "name": "with_clause"
        },
        {
          "type": "REPEAT1",
          "content": {
            "type": "SYMBOL",
            "name": "series_clause"
          }
        }
      ]
    },
    "series_clause": {
      "type": "SEQ",
      "members": [
        {
          "type": "SYMBOL",
          "name": "plot_clause"
        },
        {
          "type": "CHOICE",
          "members": [
            {
              "type": "SYMBOL",
              "name": "filter_clause"
            },
            {
              "type": "BLANK"
            }
          ]
        },
        {
          "type": "CHOICE",
          "members": [
            {
              "type": "SYMBOL",
              "name": "format_clause"
            },
            {
              "type": "BLANK"
            }
          ]
        }
      ]
    },
    "with_clause": {
      "type": "SEQ",
      "members": [
        {
          "type": "SYMBOL",
          "name": "with"
        },
        {
          "type": "SYMBOL",
          "name": "source_call"
        }
      ]
    },
    "source_call": {
      "type": "SEQ",
      "members": [
        {
          "type": "SYMBOL",
          "name": "source"
        },
        {
          "type": "STRING",
          "value": "("
        },
        {
          "type": "SYMBOL",
          "name": "string"
        },
        {
          "type": "REPEAT",
          "content": {
            "type": "SEQ",
            "members": [
              {
                "type": "STRING",
                "value": ","
              },
              {
                "type": "SYMBOL",
                "name": "string"
              }
            ]
          }
        },
        {
          "type": "STRING",
          "value": ")"
        }
      ]
    },
    "plot_clause": {
      "type": "SEQ",
      "members": [
        {
          "type": "SYMBOL",
          "name": "plot"
        },
        {
          "type": "SYMBOL",
          "name": "column_ref"
        },
        {
          "type": "SYMBOL",
          "name": "against"
        },
        {
          "type": "SYMBOL",
          "name": "column_ref"
        },
        {
          "type": "CHOICE",
          "members": [
            {
              "type": "SEQ",
              "members": [
                {
                  "type": "SYMBOL",
                  "name": "as"
                },
                {
                  "type": "SYMBOL",
                  "name": "string"
                }
              ]
            },
            {
              "type": "BLANK"
            }
          ]
        }
      ]
    },
    "filter_clause": {
      "type": "SEQ",
      "members": [
        {
          "type": "SYMBOL",
          "name": "filter"
        },
        {
          "type": "SYMBOL",
          "name": "condition"
        },
        {
          "type": "REPEAT",
          "content": {
            "type": "SEQ",
            "members": [
              {
                "type": "CHOICE",
                "members": [
                  {
                    "type": "SYMBOL",
                    "name": "and"
                  },
                  {
                    "type": "SYMBOL",
                    "name": "or"
                  }
                ]
              },
              {
                "type": "SYMBOL",
                "name": "condition"
              }
            ]
          }
        }
      ]
    },
    "condition": {
      "type": "SEQ",
      "members": [
        {
          "type": "SYMBOL",
          "name": "identifier"
        },
        {
          "type": "SYMBOL",
          "name": "operator"
        },
        {
          "type": "CHOICE",
          "members": [
            {
              "type": "SYMBOL",
              "name": "string"
            },
            {
              "type": "SYMBOL",
              "name": "number"
            },
            {
              "type": "SYMBOL",
              "name": "identifier"
            }
          ]
        }
      ]
    },
    "format_clause": {
      "type": "SEQ",
      "members": [
        {
          "type": "SYMBOL",
          "name": "format"
        },
        {
          "type": "SYMBOL",
          "name": "format_option"
        },
        {
          "type": "REPEAT",
          "content": {
            "type": "SEQ",
            "members": [
              {
                "type": "SYMBOL",
                "name": "and"
              },
              {
                "type": "SYMBOL",
                "name": "format_option"
              }
            ]
          }
        }
      ]
    },
    "format_option": {
      "type": "SEQ",
      "members": [
        {
          "type": "SYMBOL",
          "name": "identifier"
        },
        {
          "type": "STRING",
          "value": "="
        },
        {
          "type": "CHOICE",
          "members": [
            {
              "type": "SYMBOL",
              "name": "string"
            },
            {
              "type": "SYMBOL",
              "name": "number"
            },
            {
              "type": "SYMBOL",
              "name": "identifier"
            },
            {
              "type": "SYMBOL",
              "name": "null"
            }
          ]
        }
      ]
    },
    "column_ref": {
      "type": "CHOICE",
      "members": [
        {
          "type": "SYMBOL",
          "name": "identifier"
        },
        {
          "type": "SYMBOL",
          "name": "aggregate_call"
        }
      ]
    },
    "aggregate_call": {
      "type": "SEQ",
      "members": [
        {
          "type": "SYMBOL",
          "name": "aggregate_func"
        },
        {
          "type": "STRING",
          "value": "("
        },
        {
          "type": "SYMBOL",
          "name": "identifier"
        },
        {
          "type": "STRING",
          "value": ")"
        }
      ]
    },
    "with": {
      "type": "TOKEN",
      "content": {
        "type": "PREC",
        "value": 2,
        "content": {
          "type": "PATTERN",
          "value": "[Ww][Ii][Tt][Hh]"
        }
      }
    },
    "source": {
      "type": "TOKEN",
      "content": {
        "type": "PREC",
        "value": 2,
        "content": {
          "type": "PATTERN",
          "value": "[Ss][Oo][Uu][Rr][Cc][Ee]"
        }
      }
    },
    "plot": {
      "type": "TOKEN",
      "content": {
        "type": "PREC",
        "value": 2,
        "content": {
          "type": "PATTERN",
          "value": "[Pp][Ll][Oo][Tt]"
        }
      }
    },
    "against": {
      "type": "TOKEN",
      "content": {
        "type": "PREC",
        "value": 2,
        "content": {
          "type": "PATTERN",
          "value": "[Aa][Gg][Aa][Ii][Nn][Ss][Tt]"
        }
      }
    },
    "as": {
      "type": "TOKEN",
      "content": {
        "type": "PREC",
        "value": 2,
        "content": {
          "type": "PATTERN",
          "value": "[Aa][Ss]"
        }
      }
    },
    "filter": {
      "type": "TOKEN",
      "content": {
        "type": "PREC",
        "value": 2,
        "content": {
          "type": "PATTERN",
          "value": "[Ff][Ii][Ll][Tt][Ee][Rr]"
        }
      }
    },
    "and": {
      "type": "TOKEN",
      "content": {
        "type": "PREC",
        "value": 2,
        "content": {
          "type": "PATTERN",
          "value": "[Aa][Nn][Dd]"
        }
      }
    },
    "or": {
      "type": "TOKEN",
      "content": {
        "type": "PREC",
        "value": 2,
        "content": {
          "type": "PATTERN",
          "value": "[Oo][Rr]"
        }
      }
    },
    "format": {
      "type": "TOKEN",
      "content": {
        "type": "PREC",
        "value": 2,
        "content": {
          "type": "PATTERN",
          "value": "[Ff][Oo][Rr][Mm][Aa][Tt]"
        }
      }
    },
    "not": {
      "type": "TOKEN",
      "content": {
        "type": "PREC",
        "value": 2,
        "content": {
          "type": "PATTERN",
          "value": "[Nn][Oo][Tt]"
        }
      }
    },
    "null": {
      "type": "TOKEN",
      "content": {
        "type": "PREC",
        "value": 2,
        "content": {
          "type": "PATTERN",
          "value": "[Nn][Uu][Ll][Ll]"
        }
      }
    },
    "aggregate_func": {
      "type": "TOKEN",
      "content": {
        "type": "PREC",
        "value": 2,
        "content": {
          "type": "PATTERN",
          "value": "[Cc][Oo][Uu][Nn][Tt]|[Ss][Uu][Mm]|[Aa][Vv][Gg]|[Mm][Ii][Nn]|[Mm][Aa][Xx]|[Mm][Ee][Dd][Ii][Aa][Nn]"
        }
      }
    },
    "string": {
      "type": "CHOICE",
      "members": [
        {
          "type": "PATTERN",
          "value": "'[^']*'"
        },
        {
          "type": "PATTERN",
          "value": "\"[^\"]*\""
        }
      ]
    },
    "number": {
      "type": "PATTERN",
      "value": "-?\\d+\\.?\\d*"
    },
    "identifier": {
      "type": "PATTERN",
      "value": "[a-zA-Z_][a-zA-Z0-9_]*"
    },
    "operator": {
      "type": "CHOICE",
      "members": [
        {
          "type": "STRING",
          "value": "<="
        },
        {
          "type": "STRING",
          "value": ">="
        },
        {
          "type": "STRING",
          "value": "!="
        },
        {
          "type": "STRING",
          "value": "<"
        },
        {
          "type": "STRING",
          "value": ">"
        },
        {
          "type": "STRING",
          "value": "="
        }
      ]
    }
  },
  "extras": [
    {
      "type": "PATTERN",
      "value": "\\s+"
    }
  ],
  "conflicts": [],
  "precedences": [],
  "externals": [],
  "inline": [],
  "supertypes": []
}

